aiffel_korean_toknenizer/__init__.py
aiffel_korean_toknenizer/tokenizer.py
aiffel_korean_tokenizer-0.0.0.3.dist-info/LICENSE
aiffel_korean_tokenizer-0.0.0.3.dist-info/METADATA
aiffel_korean_tokenizer-0.0.0.3.dist-info/WHEEL
aiffel_korean_tokenizer-0.0.0.3.dist-info/top_level.txt
aiffel_korean_tokenizer-0.0.0.3.dist-info/RECORD
