Metadata-Version: 2.1
Name: aiffel-korean-tokenizer
Version: 0.0.0.3
Summary: aiffel_korean_tokenizer for node
Home-page: https://github.com/Finerestaurant/pip_distribute_demo
Author: seegong
License: MIT
Keywords: aiffel
Platform: UNKNOWN
Classifier: Programming Language :: Python :: 3
Classifier: License :: OSI Approved :: MIT License
Classifier: Operating System :: OS Independent
Requires-Python: >=3
License-File: LICENSE
Requires-Dist: tensorflow
Requires-Dist: konlpy
Requires-Dist: JPype1
